{"type":"tft-trait","version":"15.10.1","data":{"TFTTutorial_Assassin":{"id":"TFTTutorial_Assassin","name":"قاتل","image":{"full":"Trait_Icon_Assassin.png","sprite":"tft-trait0.png","group":"tft-trait","x":0,"y":0,"w":48,"h":48}},"TFTTutorial_Blademaster":{"id":"TFTTutorial_Blademaster","name":"مبارز","image":{"full":"Trait_Icon_Blademaster.png","sprite":"tft-trait0.png","group":"tft-trait","x":48,"y":0,"w":48,"h":48}},"TFTTutorial_Brawler":{"id":"TFTTutorial_Brawler","name":"مشاجر","image":{"full":"Trait_Icon_Brawler.png","sprite":"tft-trait0.png","group":"tft-trait","x":96,"y":0,"w":48,"h":48}},"TFTTutorial_Demon":{"id":"TFTTutorial_Demon","name":"شيطان","image":{"full":"Trait_Icon_Demon.png","sprite":"tft-trait0.png","group":"tft-trait","x":144,"y":0,"w":48,"h":48}},"TFTTutorial_Glacial":{"id":"TFTTutorial_Glacial","name":"جليدي","image":{"full":"Trait_Icon_Glacial.png","sprite":"tft-trait0.png","group":"tft-trait","x":192,"y":0,"w":48,"h":48}},"TFTTutorial_Gunslinger":{"id":"TFTTutorial_Gunslinger","name":"حامل سلاح","image":{"full":"Trait_Icon_Gunslinger.png","sprite":"tft-trait0.png","group":"tft-trait","x":240,"y":0,"w":48,"h":48}},"TFTTutorial_Hextech":{"id":"TFTTutorial_Hextech","name":"هيكستيك","image":{"full":"Trait_Icon_Hextech.png","sprite":"tft-trait0.png","group":"tft-trait","x":288,"y":0,"w":48,"h":48}},"TFTTutorial_Imperial":{"id":"TFTTutorial_Imperial","name":"إمبراطوري","image":{"full":"Trait_Icon_Imperial.png","sprite":"tft-trait0.png","group":"tft-trait","x":336,"y":0,"w":48,"h":48}},"TFTTutorial_Ninja":{"id":"TFTTutorial_Ninja","name":"نينجا","image":{"full":"Trait_Icon_Ninja.png","sprite":"tft-trait0.png","group":"tft-trait","x":384,"y":0,"w":48,"h":48}},"TFTTutorial_Pirate":{"id":"TFTTutorial_Pirate","name":"قرصان","image":{"full":"Trait_Icon_Pirate.png","sprite":"tft-trait0.png","group":"tft-trait","x":432,"y":0,"w":48,"h":48}},"TFTTutorial_Ranger":{"id":"TFTTutorial_Ranger","name":"حارس جوال","image":{"full":"Trait_Icon_Ranger.png","sprite":"tft-trait0.png","group":"tft-trait","x":0,"y":48,"w":48,"h":48}},"TFTTutorial_Robot":{"id":"TFTTutorial_Robot","name":"روبوت","image":{"full":"Trait_Icon_Robot.png","sprite":"tft-trait0.png","group":"tft-trait","x":48,"y":48,"w":48,"h":48}},"TFTTutorial_Shapeshifter":{"id":"TFTTutorial_Shapeshifter","name":"متغير أشكال","image":{"full":"Trait_Icon_Shapeshifter.png","sprite":"tft-trait0.png","group":"tft-trait","x":96,"y":48,"w":48,"h":48}},"TFTTutorial_Sorcerer":{"id":"TFTTutorial_Sorcerer","name":"مشعوذ","image":{"full":"Trait_Icon_Sorcerer.png","sprite":"tft-trait0.png","group":"tft-trait","x":144,"y":48,"w":48,"h":48}},"TFTTutorial_Void":{"id":"TFTTutorial_Void","name":"فويد","image":{"full":"Trait_Icon_Void.png","sprite":"tft-trait0.png","group":"tft-trait","x":192,"y":48,"w":48,"h":48}},"TFTTutorial_Wild":{"id":"TFTTutorial_Wild","name":"جامح","image":{"full":"Trait_Icon_Wild.png","sprite":"tft-trait0.png","group":"tft-trait","x":240,"y":48,"w":48,"h":48}},"TFTTutorial_Yordle":{"id":"TFTTutorial_Yordle","name":"يوردل","image":{"full":"Trait_Icon_Yordle.png","sprite":"tft-trait0.png","group":"tft-trait","x":288,"y":48,"w":48,"h":48}},"TFTTutorial_TutorialSecondary":{"id":"TFTTutorial_TutorialSecondary","name":"حارس","image":{"full":"Trait_Icon_Knight.png","sprite":"tft-trait0.png","group":"tft-trait","x":336,"y":48,"w":48,"h":48}},"TFTTutorial_TutorialPrimary":{"id":"TFTTutorial_TutorialPrimary","name":"نموذج","image":{"full":"Trait_Icon_4_Exemplar.png","sprite":"tft-trait0.png","group":"tft-trait","x":384,"y":48,"w":48,"h":48}},"TFT14_Immortal":{"id":"TFT14_Immortal","name":"كبش ذهب","image":{"full":"Trait_Icon_14_GoldenOx.TFT_Set14.png","sprite":"tft-trait0.png","group":"tft-trait","x":432,"y":48,"w":48,"h":48}},"TFT14_Cutter":{"id":"TFT14_Cutter","name":"جلاد","image":{"full":"Trait_Icon_4_Executioner.png","sprite":"tft-trait0.png","group":"tft-trait","x":0,"y":96,"w":48,"h":48}},"TFT14_Strong":{"id":"TFT14_Strong","name":"سفّاح","image":{"full":"Trait_Icon_4_Slayer.png","sprite":"tft-trait0.png","group":"tft-trait","x":48,"y":96,"w":48,"h":48}},"TFT14_Marksman":{"id":"TFT14_Marksman","name":"قناص","image":{"full":"Trait_Icon_14_Marksman.TFT_Set14.png","sprite":"tft-trait0.png","group":"tft-trait","x":96,"y":96,"w":48,"h":48}},"TFT14_Techie":{"id":"TFT14_Techie","name":"تقني","image":{"full":"Trait_Icon_14_Techie.TFT_Set14.png","sprite":"tft-trait0.png","group":"tft-trait","x":144,"y":96,"w":48,"h":48}},"TFT14_Controller":{"id":"TFT14_Controller","name":"استراتيجي","image":{"full":"Trait_Icon_9_Strategist.png","sprite":"tft-trait0.png","group":"tft-trait","x":192,"y":96,"w":48,"h":48}},"TFT14_Armorclad":{"id":"TFT14_Armorclad","name":"حصن","image":{"full":"Trait_Icon_9_Bastion.png","sprite":"tft-trait0.png","group":"tft-trait","x":240,"y":96,"w":48,"h":48}},"TFT14_Supercharge":{"id":"TFT14_Supercharge","name":"تضخيم","image":{"full":"Trait_Icon_14_Amp.TFT_Set14.png","sprite":"tft-trait0.png","group":"tft-trait","x":288,"y":96,"w":48,"h":48}},"TFT14_HotRod":{"id":"TFT14_HotRod","name":"نايترو","image":{"full":"Trait_Icon_14_NitroForge.TFT_Set14.png","sprite":"tft-trait0.png","group":"tft-trait","x":336,"y":96,"w":48,"h":48}},"TFT14_Cyberboss":{"id":"TFT14_Cyberboss","name":"زعيم سايبر","image":{"full":"Trait_Icon_14_Cyberbosses.TFT_Set14.png","sprite":"tft-trait0.png","group":"tft-trait","x":384,"y":96,"w":48,"h":48}},"TFT14_Divinicorp":{"id":"TFT14_Divinicorp","name":"حلف سامي","image":{"full":"Trait_Icon_14_Divinicorp.TFT_Set14.png","sprite":"tft-trait0.png","group":"tft-trait","x":432,"y":96,"w":48,"h":48}},"TFT14_EdgeRunner":{"id":"TFT14_EdgeRunner","name":"تقنية فائقة","image":{"full":"Trait_Icon_14_Exotech.TFT_Set14.png","sprite":"tft-trait1.png","group":"tft-trait","x":0,"y":0,"w":48,"h":48}},"TFT14_Bruiser":{"id":"TFT14_Bruiser","name":"ملاكم","image":{"full":"Trait_Icon_14_Bruiser.TFT_Set14.png","sprite":"tft-trait1.png","group":"tft-trait","x":48,"y":0,"w":48,"h":48}},"TFT14_Thirsty":{"id":"TFT14_Thirsty","name":"دينامو","image":{"full":"Trait_Icon_14_Dynamo.TFT_Set14.png","sprite":"tft-trait1.png","group":"tft-trait","x":96,"y":0,"w":48,"h":48}},"TFT14_Mob":{"id":"TFT14_Mob","name":"عصابة","image":{"full":"Trait_Icon_14_Mob.TFT_Set14.png","sprite":"tft-trait1.png","group":"tft-trait","x":144,"y":0,"w":48,"h":48}},"TFT14_Netgod":{"id":"TFT14_Netgod","name":"زعيم الشبكة","image":{"full":"Trait_Icon_14_GodoftheNet.TFT_Set14.png","sprite":"tft-trait1.png","group":"tft-trait","x":192,"y":0,"w":48,"h":48}},"TFT14_Swift":{"id":"TFT14_Swift","name":"نيران سريعة","image":{"full":"Trait_Icon_10_Rapidfire.png","sprite":"tft-trait1.png","group":"tft-trait","x":240,"y":0,"w":48,"h":48}},"TFT14_StreetDemon":{"id":"TFT14_StreetDemon","name":"عفريت الشوارع","image":{"full":"Trait_Icon_14_StreetDemon.TFT_Set14.png","sprite":"tft-trait1.png","group":"tft-trait","x":288,"y":0,"w":48,"h":48}},"TFT14_AnimaSquad":{"id":"TFT14_AnimaSquad","name":"فرقة أنيما","image":{"full":"Trait_Icon_14_AnimaSquad.TFT_Set14.png","sprite":"tft-trait1.png","group":"tft-trait","x":336,"y":0,"w":48,"h":48}},"TFT14_Suits":{"id":"TFT14_Suits","name":"أخصائي تشفير","image":{"full":"Trait_Icon_14_Cypher.TFT_Set14.png","sprite":"tft-trait1.png","group":"tft-trait","x":384,"y":0,"w":48,"h":48}},"TFT14_BallisTek":{"id":"TFT14_BallisTek","name":"روبوت القذائف","image":{"full":"Trait_Icon_14_BoomBots.TFT_Set14.png","sprite":"tft-trait1.png","group":"tft-trait","x":432,"y":0,"w":48,"h":48}},"TFT14_Vanguard":{"id":"TFT14_Vanguard","name":"طليعي","image":{"full":"Trait_Icon_12_Vanguard.TFT_Set12.png","sprite":"tft-trait1.png","group":"tft-trait","x":0,"y":48,"w":48,"h":48}},"TFT14_ViegoUniqueTrait":{"id":"TFT14_ViegoUniqueTrait","name":"قاتل الروح","image":{"full":"Trait_Icon_14_SoulKiller.TFT_Set14.png","sprite":"tft-trait1.png","group":"tft-trait","x":48,"y":48,"w":48,"h":48}},"TFT14_Overlord":{"id":"TFT14_Overlord","name":"القائد الأعلى","image":{"full":"Trait_Icon_14_Overlord.TFT_Set14.png","sprite":"tft-trait1.png","group":"tft-trait","x":96,"y":48,"w":48,"h":48}},"TFT14_Virus":{"id":"TFT14_Virus","name":"فيروس","image":{"full":"Trait_Icon_14_Virus.TFT_Set14.png","sprite":"tft-trait1.png","group":"tft-trait","x":144,"y":48,"w":48,"h":48}},"TFT10_8Bit":{"id":"TFT10_8Bit","name":"8-بت","image":{"full":"Trait_Icon_10_8Bit.png","sprite":"tft-trait1.png","group":"tft-trait","x":192,"y":48,"w":48,"h":48}},"TFT10_Classical":{"id":"TFT10_Classical","name":"مايسترو","image":{"full":"Trait_Icon_10_Classical.png","sprite":"tft-trait1.png","group":"tft-trait","x":240,"y":48,"w":48,"h":48}},"TFT10_Country":{"id":"TFT10_Country","name":"كاونتري","image":{"full":"Trait_Icon_10_Country.png","sprite":"tft-trait1.png","group":"tft-trait","x":288,"y":48,"w":48,"h":48}},"TFT10_CrowdDive":{"id":"TFT10_CrowdDive","name":"معشوق جمهور","image":{"full":"Trait_Icon_10_CrowdDiver.png","sprite":"tft-trait1.png","group":"tft-trait","x":336,"y":48,"w":48,"h":48}},"TFT10_DJ":{"id":"TFT10_DJ","name":"توزيع موسيقي","image":{"full":"Trait_Icon_10_DJ.png","sprite":"tft-trait1.png","group":"tft-trait","x":384,"y":48,"w":48,"h":48}},"TFT10_Edgelord":{"id":"TFT10_Edgelord","name":"انتهازي","image":{"full":"Trait_Icon_10_Edgelord.png","sprite":"tft-trait1.png","group":"tft-trait","x":432,"y":48,"w":48,"h":48}},"TFT10_EDM":{"id":"TFT10_EDM","name":"الألحان الراقصة","image":{"full":"Trait_Icon_10_EDM.png","sprite":"tft-trait1.png","group":"tft-trait","x":0,"y":96,"w":48,"h":48}},"TFT10_Emo":{"id":"TFT10_Emo","name":"عاطفي","image":{"full":"Trait_Icon_10_BigSad.png","sprite":"tft-trait1.png","group":"tft-trait","x":48,"y":96,"w":48,"h":48}},"TFT10_Fighter":{"id":"TFT10_Fighter","name":"محتفل","image":{"full":"Trait_Icon_10_Mosher.png","sprite":"tft-trait1.png","group":"tft-trait","x":96,"y":96,"w":48,"h":48}},"TFT10_Funk":{"id":"TFT10_Funk","name":"ديسكو","image":{"full":"Trait_Icon_10_Funk.png","sprite":"tft-trait1.png","group":"tft-trait","x":144,"y":96,"w":48,"h":48}},"TFT10_Hyperpop":{"id":"TFT10_Hyperpop","name":"هايبربوب","image":{"full":"Trait_Icon_10_Hyperpop.png","sprite":"tft-trait1.png","group":"tft-trait","x":192,"y":96,"w":48,"h":48}},"TFT10_Jazz":{"id":"TFT10_Jazz","name":"جاز","image":{"full":"Trait_Icon_10_Jazz.png","sprite":"tft-trait1.png","group":"tft-trait","x":240,"y":96,"w":48,"h":48}},"TFT10_KDA":{"id":"TFT10_KDA","name":"K/DA","image":{"full":"Trait_Icon_10_KDA.png","sprite":"tft-trait1.png","group":"tft-trait","x":288,"y":96,"w":48,"h":48}},"TFT10_Spellweaver":{"id":"TFT10_Spellweaver","name":"نسّاج السحر","image":{"full":"Trait_Icon_5_Sorcerer.png","sprite":"tft-trait1.png","group":"tft-trait","x":336,"y":96,"w":48,"h":48}},"TFT10_Dazzler":{"id":"TFT10_Dazzler","name":"مبهر","image":{"full":"Trait_Icon_4_Dazzler.png","sprite":"tft-trait1.png","group":"tft-trait","x":384,"y":96,"w":48,"h":48}},"TFT10_Pentakill":{"id":"TFT10_Pentakill","name":"فرقة بنتاكيل","image":{"full":"Trait_Icon_10_Pentakill.png","sprite":"tft-trait1.png","group":"tft-trait","x":432,"y":96,"w":48,"h":48}},"TFT10_PopBand":{"id":"TFT10_PopBand","name":"القلب الفولاذي","image":{"full":"Trait_Icon_10_Heartsteel.png","sprite":"tft-trait2.png","group":"tft-trait","x":0,"y":0,"w":48,"h":48}},"TFT10_PunkRock":{"id":"TFT10_PunkRock","name":"صاخب","image":{"full":"Trait_Icon_10_Punk.png","sprite":"tft-trait2.png","group":"tft-trait","x":48,"y":0,"w":48,"h":48}},"TFT10_IllBeats":{"id":"TFT10_IllBeats","name":"الإيقاع الضارب","image":{"full":"Trait_Icon_10_ILLBeats.png","sprite":"tft-trait2.png","group":"tft-trait","x":96,"y":0,"w":48,"h":48}},"TFT10_Breakout":{"id":"TFT10_Breakout","name":"بريك آوت","image":{"full":"Trait_Icon_10_Breakout.png","sprite":"tft-trait2.png","group":"tft-trait","x":144,"y":0,"w":48,"h":48}},"TFT10_Deadeye":{"id":"TFT10_Deadeye","name":"هيبة","image":{"full":"Trait_Icon_10_BigShot.png","sprite":"tft-trait2.png","group":"tft-trait","x":192,"y":0,"w":48,"h":48}},"TFT10_Quickshot":{"id":"TFT10_Quickshot","name":"نيران سريعة","image":{"full":"Trait_Icon_10_Rapidfire.png","sprite":"tft-trait2.png","group":"tft-trait","x":240,"y":0,"w":48,"h":48}},"TFT10_Superfan":{"id":"TFT10_Superfan","name":"معجب مخلص","image":{"full":"Trait_Icon_10_Superfan.png","sprite":"tft-trait2.png","group":"tft-trait","x":288,"y":0,"w":48,"h":48}},"TFT10_Sentinel":{"id":"TFT10_Sentinel","name":"خفير","image":{"full":"Trait_Icon_10_Warden.png","sprite":"tft-trait2.png","group":"tft-trait","x":336,"y":0,"w":48,"h":48}},"TFT10_Brawler":{"id":"TFT10_Brawler","name":"ملاكم","image":{"full":"Trait_Icon_3_Brawler.png","sprite":"tft-trait2.png","group":"tft-trait","x":384,"y":0,"w":48,"h":48}},"TFT10_Guardian":{"id":"TFT10_Guardian","name":"حارس","image":{"full":"Trait_Icon_7_Guardian.png","sprite":"tft-trait2.png","group":"tft-trait","x":432,"y":0,"w":48,"h":48}},"TFT10_TrueDamage":{"id":"TFT10_TrueDamage","name":"ترو داميج","image":{"full":"Trait_Icon_10_TrueDamage.png","sprite":"tft-trait2.png","group":"tft-trait","x":0,"y":48,"w":48,"h":48}},"TFT10_Executioner":{"id":"TFT10_Executioner","name":"جلاد","image":{"full":"Trait_Icon_4_Executioner.png","sprite":"tft-trait2.png","group":"tft-trait","x":48,"y":48,"w":48,"h":48}},"TFT10_TwoSides":{"id":"TFT10_TwoSides","name":"جوكر","image":{"full":"Trait_Icon_10_Wildcard.png","sprite":"tft-trait2.png","group":"tft-trait","x":96,"y":48,"w":48,"h":48}}}}