{"type":"tft-augment","version":"13.8.1","augment-container":{"name":"Eklenti Komuta Merkezi","image":{"full":"EOG_AugmentProp_Portrait.png","sprite":"tft-augment0.png","group":"tft-augment","x":0,"y":0,"w":48,"h":48}},"data":{"TFT6_Augment_ForceOfNature":{"id":"TFT6_Augment_ForceOfNature","name":"Taze Kan","image":{"full":"NewRecruit3.png","sprite":"tft-augment0.png","group":"tft-augment","x":48,"y":0,"w":48,"h":48}},"TFT6_Augment_FirstAidKit":{"id":"TFT6_Augment_FirstAidKit","name":"İlkyardım Çantası I","image":{"full":"FirstAidKit1.png","sprite":"tft-augment0.png","group":"tft-augment","x":96,"y":0,"w":48,"h":48}},"TFT6_Augment_MaxLevel10":{"id":"TFT6_Augment_MaxLevel10","name":"Seviye Atla!","image":{"full":"LevelUp3.png","sprite":"tft-augment0.png","group":"tft-augment","x":144,"y":0,"w":48,"h":48}},"TFT6_Augment_ItemGrabBag1":{"id":"TFT6_Augment_ItemGrabBag1","name":"Eşya Çekilişi I","image":{"full":"ItemGrabBag1.png","sprite":"tft-augment0.png","group":"tft-augment","x":192,"y":0,"w":48,"h":48}},"TFT6_Augment_ItemGrabBag2":{"id":"TFT6_Augment_ItemGrabBag2","name":"Eşya Çekilişi II","image":{"full":"ItemGrabBag3.png","sprite":"tft-augment0.png","group":"tft-augment","x":240,"y":0,"w":48,"h":48}},"TFT6_Augment_Windfall":{"id":"TFT6_Augment_Windfall","name":"Talih Kuşu","image":{"full":"Windfall3.png","sprite":"tft-augment0.png","group":"tft-augment","x":288,"y":0,"w":48,"h":48}},"TFT6_Augment_CalculatedLoss":{"id":"TFT6_Augment_CalculatedLoss","name":"Planlı Mağlubiyet","image":{"full":"CalculatedLoss2.png","sprite":"tft-augment0.png","group":"tft-augment","x":336,"y":0,"w":48,"h":48}},"TFT6_Augment_SalvageBin":{"id":"TFT6_Augment_SalvageBin","name":"Mal Kurtarma","image":{"full":"Salvage2.png","sprite":"tft-augment0.png","group":"tft-augment","x":384,"y":0,"w":48,"h":48}},"TFT6_Augment_SlowAndSteady":{"id":"TFT6_Augment_SlowAndSteady","name":"Gelişim Marşı","image":{"full":"SlowAndSteady3.png","sprite":"tft-augment0.png","group":"tft-augment","x":432,"y":0,"w":48,"h":48}},"TFT6_Augment_PortableForge":{"id":"TFT6_Augment_PortableForge","name":"Taşınabilir Ocak","image":{"full":"PortableForge2.png","sprite":"tft-augment0.png","group":"tft-augment","x":0,"y":48,"w":48,"h":48}},"TFT6_Augment_HighEndShopping":{"id":"TFT6_Augment_HighEndShopping","name":"Alışveriş Manyağı","image":{"full":"HighEnd3.png","sprite":"tft-augment0.png","group":"tft-augment","x":48,"y":48,"w":48,"h":48}},"TFT6_Augment_Diversify1":{"id":"TFT6_Augment_Diversify1","name":"Birlikten Kuvvet Doğar I","image":{"full":"StandUnited1.png","sprite":"tft-augment0.png","group":"tft-augment","x":96,"y":48,"w":48,"h":48}},"TFT6_Augment_Diversify2":{"id":"TFT6_Augment_Diversify2","name":"Birlikten Kuvvet Doğar II","image":{"full":"StandUnited2.png","sprite":"tft-augment0.png","group":"tft-augment","x":144,"y":48,"w":48,"h":48}},"TFT6_Augment_Diversify3":{"id":"TFT6_Augment_Diversify3","name":"Birlikten Kuvvet Doğar III","image":{"full":"StandUnited3.png","sprite":"tft-augment0.png","group":"tft-augment","x":192,"y":48,"w":48,"h":48}},"TFT6_Augment_BandOfThieves2":{"id":"TFT6_Augment_BandOfThieves2","name":"Hırsız Çetesi II","image":{"full":"BandThieves3.png","sprite":"tft-augment0.png","group":"tft-augment","x":240,"y":48,"w":48,"h":48}},"TFT6_Augment_Featherweights1":{"id":"TFT6_Augment_Featherweights1","name":"Tüysıkletler I","image":{"full":"Featherweights1.png","sprite":"tft-augment0.png","group":"tft-augment","x":288,"y":48,"w":48,"h":48}},"TFT6_Augment_Featherweights2":{"id":"TFT6_Augment_Featherweights2","name":"Tüysıkletler II","image":{"full":"Featherweights2.png","sprite":"tft-augment0.png","group":"tft-augment","x":336,"y":48,"w":48,"h":48}},"TFT6_Augment_Featherweights3":{"id":"TFT6_Augment_Featherweights3","name":"Tüysıkletler III","image":{"full":"Featherweights3.png","sprite":"tft-augment0.png","group":"tft-augment","x":384,"y":48,"w":48,"h":48}},"TFT6_Augment_HyperRoll":{"id":"TFT6_Augment_HyperRoll","name":"Dümenci","image":{"full":"Hyperroll2.png","sprite":"tft-augment0.png","group":"tft-augment","x":432,"y":48,"w":48,"h":48}},"TFT6_Augment_MetabolicAccelerator":{"id":"TFT6_Augment_MetabolicAccelerator","name":"Metabolizma Hızlandırıcı","image":{"full":"MetabolicAccel2.png","sprite":"tft-augment0.png","group":"tft-augment","x":0,"y":96,"w":48,"h":48}},"TFT6_Augment_MakeshiftArmor1":{"id":"TFT6_Augment_MakeshiftArmor1","name":"Eğreti Zırh I","image":{"full":"Makeshift1.png","sprite":"tft-augment0.png","group":"tft-augment","x":48,"y":96,"w":48,"h":48}},"TFT6_Augment_MakeshiftArmor2":{"id":"TFT6_Augment_MakeshiftArmor2","name":"Eğreti Zırh II","image":{"full":"Makeshift2.png","sprite":"tft-augment0.png","group":"tft-augment","x":96,"y":96,"w":48,"h":48}},"TFT6_Augment_Ascension":{"id":"TFT6_Augment_Ascension","name":"Yükseliş","image":{"full":"Ascension2.png","sprite":"tft-augment0.png","group":"tft-augment","x":144,"y":96,"w":48,"h":48}},"TFT6_Augment_BinaryAirdrop":{"id":"TFT6_Augment_BinaryAirdrop","name":"Çifte Hava İkmali","image":{"full":"BinaryAirdrop3.png","sprite":"tft-augment0.png","group":"tft-augment","x":192,"y":96,"w":48,"h":48}},"TFT6_Augment_ClearMind":{"id":"TFT6_Augment_ClearMind","name":"Zihin Açıklığı","image":{"full":"ClearMind2.png","sprite":"tft-augment0.png","group":"tft-augment","x":240,"y":96,"w":48,"h":48}},"TFT6_Augment_ThriftShop":{"id":"TFT6_Augment_ThriftShop","name":"Akıllı Harcama","image":{"full":"WiseSpending3.png","sprite":"tft-augment0.png","group":"tft-augment","x":288,"y":96,"w":48,"h":48}},"TFT6_Augment_Recombobulator":{"id":"TFT6_Augment_Recombobulator","name":"Evriştirici","image":{"full":"Recombobulator-I.png","sprite":"tft-augment0.png","group":"tft-augment","x":336,"y":96,"w":48,"h":48}},"TFT6_Augment_RadiantRelics":{"id":"TFT6_Augment_RadiantRelics","name":"Işıltılı Yadigârlar","image":{"full":"RadiantRelic-III.png","sprite":"tft-augment0.png","group":"tft-augment","x":384,"y":96,"w":48,"h":48}},"TFT6_Augment_JeweledLotus":{"id":"TFT6_Augment_JeweledLotus","name":"Mücevherli Nilüfer","image":{"full":"Jeweled-Lotus-II.png","sprite":"tft-augment0.png","group":"tft-augment","x":432,"y":96,"w":48,"h":48}},"TFT6_Augment_VerdantVeil":{"id":"TFT6_Augment_VerdantVeil","name":"Zümrüt Duvak","image":{"full":"Verdant-Veil-III.png","sprite":"tft-augment1.png","group":"tft-augment","x":0,"y":0,"w":48,"h":48}},"TFT6_Augment_TinyTitans":{"id":"TFT6_Augment_TinyTitans","name":"Minik Devler","image":{"full":"Tiny-Titans-I.png","sprite":"tft-augment1.png","group":"tft-augment","x":48,"y":0,"w":48,"h":48}},"TFT6_Augment_ComponentGrabBag":{"id":"TFT6_Augment_ComponentGrabBag","name":"Bileşen Çekilişi","image":{"full":"ComponentGrabBag-II.png","sprite":"tft-augment1.png","group":"tft-augment","x":96,"y":0,"w":48,"h":48}},"TFT6_Augment_Twins2":{"id":"TFT6_Augment_Twins2","name":"Çifte Bela II","image":{"full":"Double-Trouble-II.png","sprite":"tft-augment1.png","group":"tft-augment","x":144,"y":0,"w":48,"h":48}},"TFT6_Augment_Twins3":{"id":"TFT6_Augment_Twins3","name":"Çifte Bela III","image":{"full":"Double-Trouble-III.png","sprite":"tft-augment1.png","group":"tft-augment","x":192,"y":0,"w":48,"h":48}},"TFT6_Augment_FuturePeepers2":{"id":"TFT6_Augment_FuturePeepers2","name":"Kâhin II","image":{"full":"Future-Sight-III.png","sprite":"tft-augment1.png","group":"tft-augment","x":240,"y":0,"w":48,"h":48}},"TFT6_Augment_TrueTwos":{"id":"TFT6_Augment_TrueTwos","name":"Çalışkan İkiler","image":{"full":"True-Twos-II.png","sprite":"tft-augment1.png","group":"tft-augment","x":288,"y":0,"w":48,"h":48}},"TFT6_Augment_TriForce1":{"id":"TFT6_Augment_TriForce1","name":"Üçlü Güç I","image":{"full":"Tri-Force-I.png","sprite":"tft-augment1.png","group":"tft-augment","x":336,"y":0,"w":48,"h":48}},"TFT6_Augment_TriForce2":{"id":"TFT6_Augment_TriForce2","name":"Üçlü Güç II","image":{"full":"Tri-Force-II.png","sprite":"tft-augment1.png","group":"tft-augment","x":384,"y":0,"w":48,"h":48}},"TFT6_Augment_TriForce3":{"id":"TFT6_Augment_TriForce3","name":"Üçlü Güç III","image":{"full":"Tri-Force-III.png","sprite":"tft-augment1.png","group":"tft-augment","x":432,"y":0,"w":48,"h":48}},"TFT6_Augment_TheGoldenEgg":{"id":"TFT6_Augment_TheGoldenEgg","name":"Altın Yumurta","image":{"full":"The-Golden-Egg-III.png","sprite":"tft-augment1.png","group":"tft-augment","x":0,"y":48,"w":48,"h":48}},"TFT7_Augment_ThinkFast":{"id":"TFT7_Augment_ThinkFast","name":"Hızlı Düşün","image":{"full":"Think-Fast-III.TFT_Set7.png","sprite":"tft-augment1.png","group":"tft-augment","x":48,"y":48,"w":48,"h":48}},"TFT7_Augment_Bloodlust1":{"id":"TFT7_Augment_Bloodlust1","name":"Muharebe Eğitimi","image":{"full":"Combat-Training-II.TFT_Set7.png","sprite":"tft-augment1.png","group":"tft-augment","x":96,"y":48,"w":48,"h":48}},"TFT7_Augment_SacrificialPact":{"id":"TFT7_Augment_SacrificialPact","name":"Acımasız Akit","image":{"full":"Sacrificial-Pact-III.TFT_Set7.png","sprite":"tft-augment1.png","group":"tft-augment","x":144,"y":48,"w":48,"h":48}},"TFT7_Augment_PandorasBench":{"id":"TFT7_Augment_PandorasBench","name":"Pandora'nın Yedekleri","image":{"full":"Pandoras-Bench-I.TFT_Set7.png","sprite":"tft-augment1.png","group":"tft-augment","x":192,"y":48,"w":48,"h":48}},"TFT7_Augment_AxiomArc2":{"id":"TFT7_Augment_AxiomArc2","name":"Aksiyom Akımı II","image":{"full":"Axiom-Arc-II.TFT_Set7.png","sprite":"tft-augment1.png","group":"tft-augment","x":240,"y":48,"w":48,"h":48}},"TFT7_Augment_ClutteredMind":{"id":"TFT7_Augment_ClutteredMind","name":"Zihin Bulanıklığı","image":{"full":"Dizzy-II.TFT_Set7.png","sprite":"tft-augment1.png","group":"tft-augment","x":288,"y":48,"w":48,"h":48}},"TFT6_Augment_TradeSector":{"id":"TFT6_Augment_TradeSector","name":"Ticaret Bölgesi","image":{"full":"Trade2.png","sprite":"tft-augment1.png","group":"tft-augment","x":336,"y":48,"w":48,"h":48}},"TFT6_Augment_Distancing":{"id":"TFT6_Augment_Distancing","name":"Sürgünler I","image":{"full":"Exiles1.png","sprite":"tft-augment1.png","group":"tft-augment","x":384,"y":48,"w":48,"h":48}},"TFT6_Augment_Distancing2":{"id":"TFT6_Augment_Distancing2","name":"Sürgünler II","image":{"full":"Exiles2.png","sprite":"tft-augment1.png","group":"tft-augment","x":432,"y":48,"w":48,"h":48}},"TFT6_Augment_ThreesCompany":{"id":"TFT6_Augment_ThreesCompany","name":"Üç Aşağı Üç Yukarı","image":{"full":"Threes-Company-II.png","sprite":"tft-augment1.png","group":"tft-augment","x":0,"y":96,"w":48,"h":48}},"TFT7_Augment_UrfsGrabBag2":{"id":"TFT7_Augment_UrfsGrabBag2","name":"Urf'ün Çekilişi II","image":{"full":"Urfs-Grab-Bag-III.TFT_Set7.png","sprite":"tft-augment1.png","group":"tft-augment","x":48,"y":96,"w":48,"h":48}},"TFT7_Augment_LivingForge":{"id":"TFT7_Augment_LivingForge","name":"Yaşayan Ocak","image":{"full":"Living-Forge-III.TFT_Set7.png","sprite":"tft-augment1.png","group":"tft-augment","x":96,"y":96,"w":48,"h":48}},"TFT7_Augment_AFK":{"id":"TFT7_Augment_AFK","name":"AFK","image":{"full":"AFK-I.TFT_Set7.png","sprite":"tft-augment1.png","group":"tft-augment","x":144,"y":96,"w":48,"h":48}},"TFT7_Augment_BandOfThieves1":{"id":"TFT7_Augment_BandOfThieves1","name":"Hırsız Çetesi I","image":{"full":"BandThieves1.png","sprite":"tft-augment1.png","group":"tft-augment","x":192,"y":96,"w":48,"h":48}},"TFT7_Augment_LategameSpecialist":{"id":"TFT7_Augment_LategameSpecialist","name":"İleri Safhalarda Görüşürüz","image":{"full":"Late-Game-Specialist-I.TFT_Set7.png","sprite":"tft-augment1.png","group":"tft-augment","x":240,"y":96,"w":48,"h":48}},"TFT7_Augment_Preparation":{"id":"TFT7_Augment_Preparation","name":"Hazırlık I","image":{"full":"Preparation-I.TFT_Set7.png","sprite":"tft-augment1.png","group":"tft-augment","x":288,"y":96,"w":48,"h":48}},"TFT7_Augment_BigFriend":{"id":"TFT7_Augment_BigFriend","name":"Büyük Dost I","image":{"full":"Big-Friend-I.TFT_Set7.png","sprite":"tft-augment1.png","group":"tft-augment","x":336,"y":96,"w":48,"h":48}},"TFT7_Augment_LastStand":{"id":"TFT7_Augment_LastStand","name":"Son Direniş","image":{"full":"Last-Stand-II.TFT_Set7.png","sprite":"tft-augment1.png","group":"tft-augment","x":384,"y":96,"w":48,"h":48}},"TFT6_Augment_TargetDummies":{"id":"TFT6_Augment_TargetDummies","name":"Sahte Tanklar","image":{"full":"PhonyFrontline2.png","sprite":"tft-augment1.png","group":"tft-augment","x":432,"y":96,"w":48,"h":48}},"TFT7_Augment_CursedCrown":{"id":"TFT7_Augment_CursedCrown","name":"Lanetli Taç","image":{"full":"CursedCrown-III.TFT_Set7.png","sprite":"tft-augment2.png","group":"tft-augment","x":0,"y":0,"w":48,"h":48}},"TFT6_Augment_CyberneticImplants1":{"id":"TFT6_Augment_CyberneticImplants1","name":"Sibernetik İmplant I","image":{"full":"Cybernetic1.png","sprite":"tft-augment2.png","group":"tft-augment","x":48,"y":0,"w":48,"h":48}},"TFT6_Augment_CelestialBlessing1":{"id":"TFT6_Augment_CelestialBlessing1","name":"Semavi Lütuf I","image":{"full":"CelestialBlessing1.png","sprite":"tft-augment2.png","group":"tft-augment","x":96,"y":0,"w":48,"h":48}},"TFT6_Augment_SecondWind1":{"id":"TFT6_Augment_SecondWind1","name":"İkinci Şans I","image":{"full":"Second--Wind-I.png","sprite":"tft-augment2.png","group":"tft-augment","x":144,"y":0,"w":48,"h":48}},"TFT6_Augment_CyberneticShell1":{"id":"TFT6_Augment_CyberneticShell1","name":"Sibernetik Kabuk I","image":{"full":"Cybernetic-Shell-I.png","sprite":"tft-augment2.png","group":"tft-augment","x":192,"y":0,"w":48,"h":48}},"TFT6_Augment_CyberneticUplink1":{"id":"TFT6_Augment_CyberneticUplink1","name":"Sibernetik Aktarım I","image":{"full":"Cybernetic-Uplink-I.png","sprite":"tft-augment2.png","group":"tft-augment","x":240,"y":0,"w":48,"h":48}},"TFT6_Augment_CyberneticImplants3":{"id":"TFT6_Augment_CyberneticImplants3","name":"Sibernetik İmplant III","image":{"full":"Cybernetic3.png","sprite":"tft-augment2.png","group":"tft-augment","x":288,"y":0,"w":48,"h":48}},"TFT6_Augment_CyberneticShell3":{"id":"TFT6_Augment_CyberneticShell3","name":"Sibernetik Kabuk III","image":{"full":"Cybernetic-Shell-III.png","sprite":"tft-augment2.png","group":"tft-augment","x":336,"y":0,"w":48,"h":48}},"TFT6_Augment_CyberneticUplink3":{"id":"TFT6_Augment_CyberneticUplink3","name":"Sibernetik Aktarım III","image":{"full":"Cybernetic-Uplink-III.png","sprite":"tft-augment2.png","group":"tft-augment","x":384,"y":0,"w":48,"h":48}},"TFT6_Augment_RichGetRicher":{"id":"TFT6_Augment_RichGetRicher","name":"Servete Servet","image":{"full":"RichGetRicher2.png","sprite":"tft-augment2.png","group":"tft-augment","x":432,"y":0,"w":48,"h":48}},"TFT6_Augment_RichGetRicherPlus":{"id":"TFT6_Augment_RichGetRicherPlus","name":"Servete Servet+","image":{"full":"RichGetRicher2.png","sprite":"tft-augment2.png","group":"tft-augment","x":0,"y":48,"w":48,"h":48}},"TFT6_Augment_Electrocharge1":{"id":"TFT6_Augment_Electrocharge1","name":"Elektroşarj I","image":{"full":"Electrocharge-I.png","sprite":"tft-augment2.png","group":"tft-augment","x":48,"y":48,"w":48,"h":48}},"TFT6_Augment_LudensEcho1":{"id":"TFT6_Augment_LudensEcho1","name":"Luden'in Feryadı I","image":{"full":"Ludens-Echo-I.png","sprite":"tft-augment2.png","group":"tft-augment","x":96,"y":48,"w":48,"h":48}},"TFT6_Augment_CelestialBlessing2":{"id":"TFT6_Augment_CelestialBlessing2","name":"Semavi Lütuf II","image":{"full":"CelestialBlessing2.png","sprite":"tft-augment2.png","group":"tft-augment","x":144,"y":48,"w":48,"h":48}},"TFT6_Augment_CelestialBlessing3":{"id":"TFT6_Augment_CelestialBlessing3","name":"Semavi Lütuf III","image":{"full":"CelestialBlessing3.png","sprite":"tft-augment2.png","group":"tft-augment","x":192,"y":48,"w":48,"h":48}},"TFT6_Augment_SecondWind2":{"id":"TFT6_Augment_SecondWind2","name":"İkinci Şans II","image":{"full":"Second--Wind-II.png","sprite":"tft-augment2.png","group":"tft-augment","x":240,"y":48,"w":48,"h":48}},"TFT6_Augment_ThrillOfTheHunt1":{"id":"TFT6_Augment_ThrillOfTheHunt1","name":"Av Heyecanı I","image":{"full":"ThrillHunt1.png","sprite":"tft-augment2.png","group":"tft-augment","x":288,"y":48,"w":48,"h":48}},"TFT6_Augment_ThrillOfTheHunt2":{"id":"TFT6_Augment_ThrillOfTheHunt2","name":"Av Heyecanı II","image":{"full":"ThrillHunt2.png","sprite":"tft-augment2.png","group":"tft-augment","x":336,"y":48,"w":48,"h":48}},"TFT6_Augment_LudensEcho2":{"id":"TFT6_Augment_LudensEcho2","name":"Luden'in Feryadı II","image":{"full":"Ludens-Echo-II.png","sprite":"tft-augment2.png","group":"tft-augment","x":384,"y":48,"w":48,"h":48}},"TFT6_Augment_LudensEcho3":{"id":"TFT6_Augment_LudensEcho3","name":"Luden'in Feryadı III","image":{"full":"Ludens-Echo-III.png","sprite":"tft-augment2.png","group":"tft-augment","x":432,"y":48,"w":48,"h":48}},"TFT6_Augment_Electrocharge2":{"id":"TFT6_Augment_Electrocharge2","name":"Elektroşarj II","image":{"full":"Electrocharge-II.png","sprite":"tft-augment2.png","group":"tft-augment","x":0,"y":96,"w":48,"h":48}},"TFT6_Augment_Electrocharge3":{"id":"TFT6_Augment_Electrocharge3","name":"Elektroşarj III","image":{"full":"Electrocharge-III.png","sprite":"tft-augment2.png","group":"tft-augment","x":48,"y":96,"w":48,"h":48}},"TFT6_Augment_CyberneticImplants2":{"id":"TFT6_Augment_CyberneticImplants2","name":"Sibernetik İmplant II","image":{"full":"Cybernetic2.png","sprite":"tft-augment2.png","group":"tft-augment","x":96,"y":96,"w":48,"h":48}},"TFT6_Augment_CyberneticShell2":{"id":"TFT6_Augment_CyberneticShell2","name":"Sibernetik Kabuk II","image":{"full":"Cybernetic-Shell-II.png","sprite":"tft-augment2.png","group":"tft-augment","x":144,"y":96,"w":48,"h":48}},"TFT6_Augment_CyberneticUplink2":{"id":"TFT6_Augment_CyberneticUplink2","name":"Sibernetik Aktarım II","image":{"full":"Cybernetic-Uplink-II.png","sprite":"tft-augment2.png","group":"tft-augment","x":192,"y":96,"w":48,"h":48}},"TFT6_Augment_SunfireBoard":{"id":"TFT6_Augment_SunfireBoard","name":"Günateşi Tahtası","image":{"full":"SunfireBoard2.png","sprite":"tft-augment2.png","group":"tft-augment","x":240,"y":96,"w":48,"h":48}},"TFT6_Augment_WindfallPlus":{"id":"TFT6_Augment_WindfallPlus","name":"Talih Kuşu+","image":{"full":"Windfall3.png","sprite":"tft-augment2.png","group":"tft-augment","x":288,"y":96,"w":48,"h":48}},"TFT6_Augment_WindfallPlusPlus":{"id":"TFT6_Augment_WindfallPlusPlus","name":"Talih Kuşu++","image":{"full":"Windfall3.png","sprite":"tft-augment2.png","group":"tft-augment","x":336,"y":96,"w":48,"h":48}},"TFT7_Augment_FirstAidKit2":{"id":"TFT7_Augment_FirstAidKit2","name":"İlkyardım Çantası II","image":{"full":"FirstAidKit2.png","sprite":"tft-augment2.png","group":"tft-augment","x":384,"y":96,"w":48,"h":48}},"TFT7_Augment_BigFriend2":{"id":"TFT7_Augment_BigFriend2","name":"Büyük Dost II","image":{"full":"Big-Friend-II.TFT_Set7.png","sprite":"tft-augment2.png","group":"tft-augment","x":432,"y":96,"w":48,"h":48}},"TFT7_Augment_Preparation2":{"id":"TFT7_Augment_Preparation2","name":"Hazırlık II","image":{"full":"Preparation-II.TFT_Set7.png","sprite":"tft-augment3.png","group":"tft-augment","x":0,"y":0,"w":48,"h":48}},"TFT7_Augment_Preparation3":{"id":"TFT7_Augment_Preparation3","name":"Hazırlık III","image":{"full":"Preparation-III.TFT_Set7.png","sprite":"tft-augment3.png","group":"tft-augment","x":48,"y":0,"w":48,"h":48}},"TFT6_Augment_TradeSectorPlus":{"id":"TFT6_Augment_TradeSectorPlus","name":"Ticaret Bölgesi+","image":{"full":"Trade2.png","sprite":"tft-augment3.png","group":"tft-augment","x":96,"y":0,"w":48,"h":48}},"TFT8_Augment_ThreatMaxHealth":{"id":"TFT8_Augment_ThreatMaxHealth","name":"Tehdit Seviyesi: Azami","image":{"full":"ThreatLevelMaxiumum-II.TFT_Set8.png","sprite":"tft-augment3.png","group":"tft-augment","x":144,"y":0,"w":48,"h":48}},"TFT8_Augment_AceEmblem":{"id":"TFT8_Augment_AceEmblem","name":"Hünerli Arması","image":{"full":"Ace-Crest.TFT_Set8.png","sprite":"tft-augment3.png","group":"tft-augment","x":192,"y":0,"w":48,"h":48}},"TFT8_Augment_AceEmblem2":{"id":"TFT8_Augment_AceEmblem2","name":"Hünerli Mi Hünerli","image":{"full":"Ace-Crown.TFT_Set8.png","sprite":"tft-augment3.png","group":"tft-augment","x":240,"y":0,"w":48,"h":48}},"TFT8_Augment_ADMINEmblem":{"id":"TFT8_Augment_ADMINEmblem","name":"İ.D.A.R.E. Arması","image":{"full":"ADMIN-Crest.TFT_Set8.png","sprite":"tft-augment3.png","group":"tft-augment","x":288,"y":0,"w":48,"h":48}},"TFT8_Augment_ADMINEmblem2":{"id":"TFT8_Augment_ADMINEmblem2","name":"İ.D.A.R.E. Tacı","image":{"full":"ADMIN-Crown.TFT_Set8.png","sprite":"tft-augment3.png","group":"tft-augment","x":336,"y":0,"w":48,"h":48}},"TFT8_Augment_AnimaSquadEmblem":{"id":"TFT8_Augment_AnimaSquadEmblem","name":"Anima Timi Arması","image":{"full":"Anima-Squad-Crest.TFT_Set8.png","sprite":"tft-augment3.png","group":"tft-augment","x":384,"y":0,"w":48,"h":48}},"TFT8_Augment_AnimaSquadEmblem2":{"id":"TFT8_Augment_AnimaSquadEmblem2","name":"Anima Timi Tacı","image":{"full":"Anima-Squad-Crown.TFT_Set8.png","sprite":"tft-augment3.png","group":"tft-augment","x":432,"y":0,"w":48,"h":48}},"TFT8_Augment_BrawlerEmblem":{"id":"TFT8_Augment_BrawlerEmblem","name":"Dövüşçü Arması","image":{"full":"Brawler-Crest.TFT_Set8.png","sprite":"tft-augment3.png","group":"tft-augment","x":0,"y":48,"w":48,"h":48}},"TFT8_Augment_BrawlerEmblem2":{"id":"TFT8_Augment_BrawlerEmblem2","name":"Dövüşçü Tacı","image":{"full":"Brawler-Crown.TFT_Set8.png","sprite":"tft-augment3.png","group":"tft-augment","x":48,"y":48,"w":48,"h":48}},"TFT8_Augment_ChannelerEmblem":{"id":"TFT8_Augment_ChannelerEmblem","name":"Büyüşor Arması","image":{"full":"Spellslinger-Crest.TFT_Set8.png","sprite":"tft-augment3.png","group":"tft-augment","x":96,"y":48,"w":48,"h":48}},"TFT8_Augment_ChannelerEmblem2":{"id":"TFT8_Augment_ChannelerEmblem2","name":"Büyüşor Tacı","image":{"full":"Spellslinger-Crown.TFT_Set8.png","sprite":"tft-augment3.png","group":"tft-augment","x":144,"y":48,"w":48,"h":48}},"TFT8_Augment_DeadeyeEmblem":{"id":"TFT8_Augment_DeadeyeEmblem","name":"Kesinatış Arması","image":{"full":"Sureshot-Crest.TFT_Set8.png","sprite":"tft-augment3.png","group":"tft-augment","x":192,"y":48,"w":48,"h":48}},"TFT8_Augment_DeadeyeEmblem2":{"id":"TFT8_Augment_DeadeyeEmblem2","name":"Kesinatış Tacı","image":{"full":"Sureshot-Crown.TFT_Set8.png","sprite":"tft-augment3.png","group":"tft-augment","x":240,"y":48,"w":48,"h":48}},"TFT8_Augment_DefenderEmblem":{"id":"TFT8_Augment_DefenderEmblem","name":"Savunucu Arması","image":{"full":"Defender-Crest.TFT_Set8.png","sprite":"tft-augment3.png","group":"tft-augment","x":288,"y":48,"w":48,"h":48}},"TFT8_Augment_DefenderEmblem2":{"id":"TFT8_Augment_DefenderEmblem2","name":"Savunucu Tacı","image":{"full":"Defender-Crown.TFT_Set8.png","sprite":"tft-augment3.png","group":"tft-augment","x":336,"y":48,"w":48,"h":48}},"TFT8_Augment_DuelistEmblem":{"id":"TFT8_Augment_DuelistEmblem","name":"Düellocu Arması","image":{"full":"Duelist-Crest.TFT_Set8.png","sprite":"tft-augment3.png","group":"tft-augment","x":384,"y":48,"w":48,"h":48}},"TFT8_Augment_DuelistEmblem2":{"id":"TFT8_Augment_DuelistEmblem2","name":"Düellocu Tacı","image":{"full":"Duelist-Crown.TFT_Set8.png","sprite":"tft-augment3.png","group":"tft-augment","x":432,"y":48,"w":48,"h":48}},"TFT8_Augment_ExoPrimeEmblem":{"id":"TFT8_Augment_ExoPrimeEmblem","name":"Meka: ÖNCÜ Arması","image":{"full":"Mecha-Prime-Crest.TFT_Set8.png","sprite":"tft-augment3.png","group":"tft-augment","x":0,"y":96,"w":48,"h":48}},"TFT8_Augment_ExoPrimeEmblem2":{"id":"TFT8_Augment_ExoPrimeEmblem2","name":"Meka: ÖNCÜ Tacı","image":{"full":"Mecha-Prime-Crown.TFT_Set8.png","sprite":"tft-augment3.png","group":"tft-augment","x":48,"y":96,"w":48,"h":48}},"TFT8_Augment_AegisEmblem":{"id":"TFT8_Augment_AegisEmblem","name":"Siper Arması","image":{"full":"Aegis-Crest.TFT_Set8.png","sprite":"tft-augment3.png","group":"tft-augment","x":96,"y":96,"w":48,"h":48}},"TFT8_Augment_AegisEmblem2":{"id":"TFT8_Augment_AegisEmblem2","name":"Siper Tacı","image":{"full":"Aegis-Crown.TFT_Set8.png","sprite":"tft-augment3.png","group":"tft-augment","x":144,"y":96,"w":48,"h":48}},"TFT8_Augment_HackerEmblem":{"id":"TFT8_Augment_HackerEmblem","name":"Hacker Arması","image":{"full":"Hacker-Crest.TFT_Set8.png","sprite":"tft-augment3.png","group":"tft-augment","x":192,"y":96,"w":48,"h":48}},"TFT8_Augment_HackerEmblem2":{"id":"TFT8_Augment_HackerEmblem2","name":"Hacker Tacı","image":{"full":"Hacker-Crown.TFT_Set8.png","sprite":"tft-augment3.png","group":"tft-augment","x":240,"y":96,"w":48,"h":48}},"TFT8_Augment_HeartEmblem":{"id":"TFT8_Augment_HeartEmblem","name":"Yürek Arması","image":{"full":"Heart-Crest.TFT_Set8.png","sprite":"tft-augment3.png","group":"tft-augment","x":288,"y":96,"w":48,"h":48}},"TFT8_Augment_HeartEmblem2":{"id":"TFT8_Augment_HeartEmblem2","name":"Yürek Tacı","image":{"full":"Heart-Crown.TFT_Set8.png","sprite":"tft-augment3.png","group":"tft-augment","x":336,"y":96,"w":48,"h":48}},"TFT8_Augment_MascotEmblem":{"id":"TFT8_Augment_MascotEmblem","name":"Maskot Arması","image":{"full":"Mascot-Crest.TFT_Set8.png","sprite":"tft-augment3.png","group":"tft-augment","x":384,"y":96,"w":48,"h":48}},"TFT8_Augment_MascotEmblem2":{"id":"TFT8_Augment_MascotEmblem2","name":"Maskot Tacı","image":{"full":"Mascot-Crown.TFT_Set8.png","sprite":"tft-augment3.png","group":"tft-augment","x":432,"y":96,"w":48,"h":48}},"TFT8_Augment_OxForceEmblem":{"id":"TFT8_Augment_OxForceEmblem","name":"Boğa Kuvveti Arması","image":{"full":"Ox-Force-Crest.TFT_Set8.png","sprite":"tft-augment4.png","group":"tft-augment","x":0,"y":0,"w":48,"h":48}},"TFT8_Augment_OxForceEmblem2":{"id":"TFT8_Augment_OxForceEmblem2","name":"Boğa Kuvveti Tacı","image":{"full":"Ox-Force-Crown.TFT_Set8.png","sprite":"tft-augment4.png","group":"tft-augment","x":48,"y":0,"w":48,"h":48}},"TFT8_Augment_PranksterEmblem":{"id":"TFT8_Augment_PranksterEmblem","name":"Şakacı Arması","image":{"full":"Prankster-Crest.TFT_Set8.png","sprite":"tft-augment4.png","group":"tft-augment","x":96,"y":0,"w":48,"h":48}},"TFT8_Augment_PranksterEmblem2":{"id":"TFT8_Augment_PranksterEmblem2","name":"Şakacı Tacı","image":{"full":"Prankster-Crown.TFT_Set8.png","sprite":"tft-augment4.png","group":"tft-augment","x":144,"y":0,"w":48,"h":48}},"TFT8_Augment_RenegadeEmblem":{"id":"TFT8_Augment_RenegadeEmblem","name":"İsyankâr Arması","image":{"full":"Renegade-Crest.TFT_Set8.png","sprite":"tft-augment4.png","group":"tft-augment","x":192,"y":0,"w":48,"h":48}},"TFT8_Augment_RenegadeEmblem2":{"id":"TFT8_Augment_RenegadeEmblem2","name":"İsyankâr Tacı","image":{"full":"Renegade-Crown.TFT_Set8.png","sprite":"tft-augment4.png","group":"tft-augment","x":240,"y":0,"w":48,"h":48}},"TFT8_Augment_StarGuardianEmblem":{"id":"TFT8_Augment_StarGuardianEmblem","name":"Yıldız Muhafızı Arması","image":{"full":"Star-Guardian-Crest.TFT_Set8.png","sprite":"tft-augment4.png","group":"tft-augment","x":288,"y":0,"w":48,"h":48}},"TFT8_Augment_StarGuardianEmblem2":{"id":"TFT8_Augment_StarGuardianEmblem2","name":"Yıldız Muhafızı Tacı","image":{"full":"Star-Guardian-Crown.TFT_Set8.png","sprite":"tft-augment4.png","group":"tft-augment","x":336,"y":0,"w":48,"h":48}},"TFT8_Augment_UndergroundTheTrait2":{"id":"TFT8_Augment_UndergroundTheTrait2","name":"Yeraltı Ruhu","image":{"full":"The-Underground-Crown-III.TFT_Set8.png","sprite":"tft-augment4.png","group":"tft-augment","x":384,"y":0,"w":48,"h":48}},"TFT6_Augment_WoodlandCharm":{"id":"TFT6_Augment_WoodlandCharm","name":"Peri Tılsımı","image":{"full":"WoodlandCharm3.png","sprite":"tft-augment4.png","group":"tft-augment","x":432,"y":0,"w":48,"h":48}},"TFT7_Augment_LuckyGloves":{"id":"TFT7_Augment_LuckyGloves","name":"Şanslı Eldiven","image":{"full":"Lucky-Gloves-III.png","sprite":"tft-augment4.png","group":"tft-augment","x":0,"y":48,"w":48,"h":48}},"TFT7_Augment_ScopedWeapons1":{"id":"TFT7_Augment_ScopedWeapons1","name":"Dürbünlü Silahlar I","image":{"full":"ScopedWeapons2.png","sprite":"tft-augment4.png","group":"tft-augment","x":48,"y":48,"w":48,"h":48}},"TFT6_Augment_Battlemage1":{"id":"TFT6_Augment_Battlemage1","name":"Savaş Büyücüsü I","image":{"full":"Battlemage-I-A.png","sprite":"tft-augment4.png","group":"tft-augment","x":96,"y":48,"w":48,"h":48}},"TFT6_Augment_Battlemage2":{"id":"TFT6_Augment_Battlemage2","name":"Savaş Büyücüsü II","image":{"full":"Battlemage-II-A.png","sprite":"tft-augment4.png","group":"tft-augment","x":144,"y":48,"w":48,"h":48}},"TFT6_Augment_Battlemage3":{"id":"TFT6_Augment_Battlemage3","name":"Savaş Büyücüsü III","image":{"full":"Battlemage-III-A.png","sprite":"tft-augment4.png","group":"tft-augment","x":192,"y":48,"w":48,"h":48}},"TFT6_Augment_MeleeStarBlade1":{"id":"TFT6_Augment_MeleeStarBlade1","name":"Bıçak Sırtı I","image":{"full":"CQCTraining1.png","sprite":"tft-augment4.png","group":"tft-augment","x":240,"y":48,"w":48,"h":48}},"TFT6_Augment_MeleeStarBlade2":{"id":"TFT6_Augment_MeleeStarBlade2","name":"Bıçak Sırtı II","image":{"full":"CQCTraining2.png","sprite":"tft-augment4.png","group":"tft-augment","x":288,"y":48,"w":48,"h":48}},"TFT6_Augment_MeleeStarBlade3":{"id":"TFT6_Augment_MeleeStarBlade3","name":"Bıçak Sırtı III","image":{"full":"CQCTraining3.png","sprite":"tft-augment4.png","group":"tft-augment","x":336,"y":48,"w":48,"h":48}},"TFT7_Augment_BirthdayPresents":{"id":"TFT7_Augment_BirthdayPresents","name":"Doğum Günü Hediyesi","image":{"full":"Golden-Gifts-III.png","sprite":"tft-augment4.png","group":"tft-augment","x":384,"y":48,"w":48,"h":48}},"TFT7_Augment_Consistency":{"id":"TFT7_Augment_Consistency","name":"İstikrar","image":{"full":"Consistency-I.png","sprite":"tft-augment4.png","group":"tft-augment","x":432,"y":48,"w":48,"h":48}},"TFT8_Augment_AnimaSquadTrait":{"id":"TFT8_Augment_AnimaSquadTrait","name":"Anima Timi Yüreği","image":{"full":"Anima-Squad-Heart.TFT_Set8.png","sprite":"tft-augment4.png","group":"tft-augment","x":0,"y":96,"w":48,"h":48}},"TFT8_Augment_StarGuardianTrait":{"id":"TFT8_Augment_StarGuardianTrait","name":"Yıldız Muhafızı Yüreği","image":{"full":"Star-Guardian-Heart.TFT_Set8.png","sprite":"tft-augment4.png","group":"tft-augment","x":48,"y":96,"w":48,"h":48}},"TFT8_Augment_InterPolarisTrait":{"id":"TFT8_Augment_InterPolarisTrait","name":"Lazer Birliği Yüreği","image":{"full":"Lasercorps-Heart-II.TFT_Set8.png","sprite":"tft-augment4.png","group":"tft-augment","x":96,"y":96,"w":48,"h":48}},"TFT8_Augment_OxForceTrait":{"id":"TFT8_Augment_OxForceTrait","name":"Boğa Kuvveti Yüreği","image":{"full":"Ox-Force-Heart.TFT_Set8.png","sprite":"tft-augment4.png","group":"tft-augment","x":144,"y":96,"w":48,"h":48}},"TFT8_Augment_GenAETrait":{"id":"TFT8_Augment_GenAETrait","name":"Devingenç Yüreği","image":{"full":"Gadgeteens-Heart-I.TFT_Set8.png","sprite":"tft-augment4.png","group":"tft-augment","x":192,"y":96,"w":48,"h":48}},"TFT8_Augment_MascotTrait":{"id":"TFT8_Augment_MascotTrait","name":"Maskot Yüreği","image":{"full":"Mascot-Heart.TFT_Set8.png","sprite":"tft-augment4.png","group":"tft-augment","x":240,"y":96,"w":48,"h":48}},"TFT8_Augment_DefenderTrait":{"id":"TFT8_Augment_DefenderTrait","name":"Savunucu Yüreği","image":{"full":"Defender-Heart.TFT_Set8.png","sprite":"tft-augment4.png","group":"tft-augment","x":288,"y":96,"w":48,"h":48}},"TFT8_Augment_ChannelerTrait":{"id":"TFT8_Augment_ChannelerTrait","name":"Büyüşor Yüreği","image":{"full":"Spellslinger-Heart.TFT_Set8.png","sprite":"tft-augment4.png","group":"tft-augment","x":336,"y":96,"w":48,"h":48}},"TFT8_Augment_BrawlerTrait":{"id":"TFT8_Augment_BrawlerTrait","name":"Dövüşçü Yüreği","image":{"full":"Brawler-Heart.TFT_Set8.png","sprite":"tft-augment4.png","group":"tft-augment","x":384,"y":96,"w":48,"h":48}},"TFT8_Augment_DuelistTrait":{"id":"TFT8_Augment_DuelistTrait","name":"Düellocu Yüreği","image":{"full":"Duelist-Heart.TFT_Set8.png","sprite":"tft-augment4.png","group":"tft-augment","x":432,"y":96,"w":48,"h":48}},"TFT8_Augment_HeartTrait":{"id":"TFT8_Augment_HeartTrait","name":"Yürek Yüreği","image":{"full":"Heart-Heart.TFT_Set8.png","sprite":"tft-augment5.png","group":"tft-augment","x":0,"y":0,"w":48,"h":48}},"TFT8_Augment_DeadeyeTrait":{"id":"TFT8_Augment_DeadeyeTrait","name":"Kesinatış Yüreği","image":{"full":"Sureshot-Heart.TFT_Set8.png","sprite":"tft-augment5.png","group":"tft-augment","x":48,"y":0,"w":48,"h":48}},"TFT8_Augment_RenegadeTrait":{"id":"TFT8_Augment_RenegadeTrait","name":"İsyankâr Yüreği","image":{"full":"Renegade-Heart.TFT_Set8.png","sprite":"tft-augment5.png","group":"tft-augment","x":96,"y":0,"w":48,"h":48}},"TFT8_Augment_UndergroundTheTrait":{"id":"TFT8_Augment_UndergroundTheTrait","name":"Yeraltı Yüreği","image":{"full":"The-Underground-Heart-II.TFT_Set8.png","sprite":"tft-augment5.png","group":"tft-augment","x":144,"y":0,"w":48,"h":48}},"TFT8_Augment_SupersTrait":{"id":"TFT8_Augment_SupersTrait","name":"Süper Kahraman Yüreği","image":{"full":"Supers-Heart-II.TFT_Set8.png","sprite":"tft-augment5.png","group":"tft-augment","x":192,"y":0,"w":48,"h":48}},"TFT8_Augment_SupersTrait2":{"id":"TFT8_Augment_SupersTrait2","name":"Süper Kahraman Ruhu","image":{"full":"Supers-Crown-III.TFT_Set8.png","sprite":"tft-augment5.png","group":"tft-augment","x":240,"y":0,"w":48,"h":48}},"TFT8_Augment_ADMINTrait":{"id":"TFT8_Augment_ADMINTrait","name":"İ.D.A.R.E. Yüreği","image":{"full":"ADMIN-Heart.TFT_Set8.png","sprite":"tft-augment5.png","group":"tft-augment","x":288,"y":0,"w":48,"h":48}},"TFT8_Augment_HackerTrait":{"id":"TFT8_Augment_HackerTrait","name":"Hacker Yüreği","image":{"full":"Hacker-Heart.TFT_Set8.png","sprite":"tft-augment5.png","group":"tft-augment","x":336,"y":0,"w":48,"h":48}},"TFT6_Augment_TomeOfTraits1":{"id":"TFT6_Augment_TomeOfTraits1","name":"Antik Arşiv I","image":{"full":"AncientArchives2.png","sprite":"tft-augment5.png","group":"tft-augment","x":384,"y":0,"w":48,"h":48}},"TFT7_Augment_TomeOfTraits2":{"id":"TFT7_Augment_TomeOfTraits2","name":"Antik Arşiv II","image":{"full":"AncientArchives3.png","sprite":"tft-augment5.png","group":"tft-augment","x":432,"y":0,"w":48,"h":48}},"TFT6_Augment_Traitless2":{"id":"TFT6_Augment_Traitless2","name":"Farklıyım İşte II","image":{"full":"BuiltDifferent2.png","sprite":"tft-augment5.png","group":"tft-augment","x":0,"y":48,"w":48,"h":48}},"TFT6_Augment_Traitless3":{"id":"TFT6_Augment_Traitless3","name":"Farklıyım İşte III","image":{"full":"BuiltDifferent3.png","sprite":"tft-augment5.png","group":"tft-augment","x":48,"y":48,"w":48,"h":48}},"TFT6_Augment_FuturePeepers":{"id":"TFT6_Augment_FuturePeepers","name":"Kâhin I","image":{"full":"Future-Sight-I.png","sprite":"tft-augment5.png","group":"tft-augment","x":96,"y":48,"w":48,"h":48}},"TFT6_Augment_GachaAddict":{"id":"TFT6_Augment_GachaAddict","name":"Altın Bilet","image":{"full":"GoldenTicket3.png","sprite":"tft-augment5.png","group":"tft-augment","x":144,"y":48,"w":48,"h":48}},"TFT8_Augment_InfiniteamTrait":{"id":"TFT8_Augment_InfiniteamTrait","name":"Sonsuzluk Timi Yüreği","image":{"full":"InfiniTeam-Heart-I.TFT_Set8_Stage2.png","sprite":"tft-augment5.png","group":"tft-augment","x":192,"y":48,"w":48,"h":48}},"TFT8_Augment_InfiniteamEmblem":{"id":"TFT8_Augment_InfiniteamEmblem","name":"Sonsuzluk Timi Arması","image":{"full":"InfiniTeam-Crest-II.TFT_Set8_Stage2.png","sprite":"tft-augment5.png","group":"tft-augment","x":240,"y":48,"w":48,"h":48}},"TFT8_Augment_QuickdrawTrait":{"id":"TFT8_Augment_QuickdrawTrait","name":"Hızlı Tetik Yüreği","image":{"full":"Quickdraw-Heart-II.TFT_Set8_Stage2.png","sprite":"tft-augment5.png","group":"tft-augment","x":288,"y":48,"w":48,"h":48}},"TFT8_Augment_QuickdrawTrait2":{"id":"TFT8_Augment_QuickdrawTrait2","name":"Hızlı Tetik Ruhu","image":{"full":"Quickdraw-Crown-III.TFT_Set8_Stage2.png","sprite":"tft-augment5.png","group":"tft-augment","x":336,"y":48,"w":48,"h":48}},"TFT8_Augment_RiftwalkerEmblem":{"id":"TFT8_Augment_RiftwalkerEmblem","name":"Boşluk Gezgini Arması","image":{"full":"Riftwalker-Crest-II.TFT_Set8_Stage2.png","sprite":"tft-augment5.png","group":"tft-augment","x":384,"y":48,"w":48,"h":48}},"TFT8_Augment_RiftwalkerEmblem2":{"id":"TFT8_Augment_RiftwalkerEmblem2","name":"Boşluk Gezgini Tacı","image":{"full":"Riftwalker-Crown-III.TFT_Set8_Stage2.png","sprite":"tft-augment5.png","group":"tft-augment","x":432,"y":48,"w":48,"h":48}},"TFT8_Augment_GenAEEmblem":{"id":"TFT8_Augment_GenAEEmblem","name":"Devingenç Arması","image":{"full":"Gadgeteens-Crest-II.TFT_Set8.png","sprite":"tft-augment5.png","group":"tft-augment","x":0,"y":96,"w":48,"h":48}},"TFT8_Augment_GenAEEmblem2":{"id":"TFT8_Augment_GenAEEmblem2","name":"Devingenç Tacı","image":{"full":"Gadgeteens-Crown-III.TFT_Set8.png","sprite":"tft-augment5.png","group":"tft-augment","x":48,"y":96,"w":48,"h":48}},"TFT8_Augment_InfiniteamEmblem2":{"id":"TFT8_Augment_InfiniteamEmblem2","name":"Sonsuzluk Timi Tacı","image":{"full":"InfiniTeam-Crown-III.TFT_Set8_Stage2.png","sprite":"tft-augment5.png","group":"tft-augment","x":96,"y":96,"w":48,"h":48}},"TFT6_Augment_PandorasItems":{"id":"TFT6_Augment_PandorasItems","name":"Pandora'nın Eşyaları","image":{"full":"Pandora1.png","sprite":"tft-augment5.png","group":"tft-augment","x":144,"y":96,"w":48,"h":48}},"TFT8_Augment_SalvageBinPlus":{"id":"TFT8_Augment_SalvageBinPlus","name":"Mal Kurtarma+","image":{"full":"Salvage2.png","sprite":"tft-augment5.png","group":"tft-augment","x":192,"y":96,"w":48,"h":48}},"TFT8_Augment_InterPolarisTrait2":{"id":"TFT8_Augment_InterPolarisTrait2","name":"Lazer Birliği Ruhu","image":{"full":"Lasercorps-Crown-III.TFT_Set8.png","sprite":"tft-augment5.png","group":"tft-augment","x":240,"y":96,"w":48,"h":48}}}}